{
  "version": "6.1.1",
  "flags": {},
  "shapes": [
    {
      "label": "container_code",
      "points": [
        [
          410.2234636871508,
          131.11731843575419
        ],
        [
          500.1675977653631,
          141.731843575419
        ]
      ],
      "group_id": null,
      "description": "",
      "shape_type": "rectangle",
      "flags": {},
      "mask": null
    }
  ],
  "imagePath": "frame_631400.jpg",
  "imageData": null,
  "imageHeight": 360,
  "imageWidth": 640
}